{
  "name": "Beast",
  "type": "agenda",
  "img": "icons/svg/item-bag.svg",
  "folder": "yflwz1gIcGFia1OT",
  "system": {
    "agendaName": "Beast",
    "formula": "",
    "unboldedTasks": [
      "aTcATfYgBD84nTpp"
    ],
    "boldedTasks": [
      "pHRIjb6D9Ru6WhvE"
    ],
    "abilities": [
      "h9OZQZvbIyX6U2Me",
      "NvAYgb5gbaWgSoaa",
      "dmeIePhZHY3hq3UQ",
      "HOvpZhh2TpNWyr02",
      "WckuRbL36XWVk6F2"
    ],
    "description": ""
  },
  "_id": "Z6L38ahpokWSO04i",
  "effects": [],
  "sort": 100000,
  "ownership": {
    "default": 0,
    "yJuxhbSZPW8Smq1z": 3,
    "FezNQLnArNIsRQJJ": 3
  },
  "flags": {},
  "_stats": {
    "compendiumSource": null,
    "duplicateSource": null,
    "coreVersion": "12.331",
    "systemId": "cain",
    "systemVersion": "1.0.20",
    "createdTime": 1724996336702,
    "modifiedTime": 1724996336702,
    "lastModifiedBy": "FezNQLnArNIsRQJJ"
  },
  "_key": "!items!Z6L38ahpokWSO04i"
}
